[
{"Order":"88888888","Inspection Lot":"22222222222","Material":"11111111","Material Description":"Noodles 2 Min","Date Result entry":"09/26/2020","Time result entry":"04:30:49 AM","Insp Point Identification":"20200926|043046|","Work center":"NLEPACK2","Operation Description":"NPL 2@ End of shift","Short Text Insp Char":"ACCBLNCE","Target Value":"","Upper Tol Limit":"","Lower Tol Limit":"","Attribute":"","Unit of Measure":"","Char Valuation":"A","Code Catalog":"001","Code Description":"OK","User ID result entry":"USERNAME3","QT Result":"NOK"},
{"Order":"88888888","Inspection Lot":"22222222222","Material":"11111111","Material Description":"Noodles 2 Min","Date Result entry":"09/25/2020","Time result entry":"01:49:38 PM","Insp Point Identification":"20200925|134934|","Work center":"NLEPACK2","Operation Description":"NPL 2@ End of shift","Short Text Insp Char":"ACCBLNCE","Target Value":"","Upper Tol Limit":"","Lower Tol Limit":"","Attribute":"","Unit of Measure":"","Char Valuation":"A","Code Catalog":"001","Code Description":"OK","User ID result entry":"USERNAME2","QT Result":"NOK"},
{"Order":"88888888","Inspection Lot":"22222222222","Material":"11111111","Material Description":"Noodles 2 Min","Date Result entry":"09/25/2020","Time result entry":"09:26:47 PM","Insp Point Identification":"20200925|212643|","Work center":"NLEPACK2","Operation Description":"NPL 2@ End of shift","Short Text Insp Char":"ACCBLNCE","Target Value":"","Upper Tol Limit":"","Lower Tol Limit":"","Attribute":"","Unit of Measure":"","Char Valuation":"A","Code Catalog":"001","Code Description":"OK","User ID result entry":"USERNAME3","QT Result":"NOK"},
{"Order":"88888888","Inspection Lot":"22222222222","Material":"11111111","Material Description":"Noodles 2 Min","Date Result entry":"09/26/2020","Time result entry":"04:30:38 AM","Insp Point Identification":"20200926|043034|","Work center":"NLEPACK2","Operation Description":"NPL 2@ End of each Batch","Short Text Insp Char":"AVNW Check","Target Value":"","Upper Tol Limit":"","Lower Tol Limit":"","Attribute":"","Unit of Measure":"","Char Valuation":"A","Code Catalog":"001","Code Description":"OK","User ID result entry":"USERNAME3","QT Result":"OK"},
{"Order":"88888888","Inspection Lot":"22222222222","Material":"11111111","Material Description":"Noodles 2 Min","Date Result entry":"09/25/2020","Time result entry":"01:49:51 PM","Insp Point Identification":"20200925|134946|","Work center":"NLEPACK2","Operation Description":"NPL 2@ End of each Batch","Short Text Insp Char":"AVNW Check","Target Value":"","Upper Tol Limit":"","Lower Tol Limit":"","Attribute":"","Unit of Measure":"","Char Valuation":"A","Code Catalog":"001","Code Description":"OK","User ID result entry":"USERNAME2","QT Result":"NOK"},
{"Order":"88888888","Inspection Lot":"22222222222","Material":"11111111","Material Description":"Noodles 2 Min","Date Result entry":"09/26/2020","Time result entry":"04:30:48 AM","Insp Point Identification":"20200926|043046|","Work center":"NLEPACK2","Operation Description":"NPL 2@ End of shift","Short Text Insp Char":"BSLVL Check","Target Value":"","Upper Tol Limit":"","Lower Tol Limit":"","Attribute":"","Unit of Measure":"","Char Valuation":"A","Code Catalog":"001","Code Description":"OK","User ID result entry":"USERNAME3","QT Result":"OK"},
{"Order":"88888888","Inspection Lot":"22222222222","Material":"11111111","Material Description":"Noodles 2 Min","Date Result entry":"09/25/2020","Time result entry":"01:49:38 PM","Insp Point Identification":"20200925|134934|","Work center":"NLEPACK2","Operation Description":"NPL 2@ End of shift","Short Text Insp Char":"BSLVL Check","Target Value":"","Upper Tol Limit":"","Lower Tol Limit":"","Attribute":"","Unit of Measure":"","Char Valuation":"A","Code Catalog":"001","Code Description":"OK","User ID result entry":"USERNAME2","QT Result":"OK"},
{"Order":"88888888","Inspection Lot":"22222222222","Material":"11111111","Material Description":"Noodles 2 Min","Date Result entry":"09/25/2020","Time result entry":"09:26:46 PM","Insp Point Identification":"20200925|212643|","Work center":"NLEPACK2","Operation Description":"NPL 2@ End of shift","Short Text Insp Char":"BSLVL Check","Target Value":"","Upper Tol Limit":"","Lower Tol Limit":"","Attribute":"","Unit of Measure":"","Char Valuation":"A","Code Catalog":"001","Code Description":"OK","User ID result entry":"USERNAME3","QT Result":"OK"},
{"Order":"88888888","Inspection Lot":"22222222222","Material":"11111111","Material Description":"Noodles 2 Min","Date Result entry":"09/26/2020","Time result entry":"04:30:20 AM","Insp Point Identification":"20200926|043017|","Work center":"NLEPACK2","Operation Description":"NPL 2@ End of Production","Short Text Insp Char":"CAF Check","Target Value":"","Upper Tol Limit":"","Lower Tol Limit":"","Attribute":"","Unit of Measure":"","Char Valuation":"A","Code Catalog":"001","Code Description":"OK","User ID result entry":"USERNAME3","QT Result":"NOK"},
{"Order":"88888888","Inspection Lot":"22222222222","Material":"11111111","Material Description":"Noodles 2 Min","Date Result entry":"09/26/2020","Time result entry":"01:36:45 AM","Insp Point Identification":"20200926|013517|","Work center":"NLEPACK2","Operation Description":"NPL 2@ Every 4Hr","Short Text Insp Char":"COMFONPCK Check","Target Value":"","Upper Tol Limit":"","Lower Tol Limit":"","Attribute":"","Unit of Measure":"","Char Valuation":"A","Code Catalog":"001","Code Description":"OK","User ID result entry":"USERNAME5","QT Result":"OK"},
{"Order":"88888888","Inspection Lot":"22222222222","Material":"11111111","Material Description":"Noodles 2 Min","Date Result entry":"09/25/2020","Time result entry":"09:30:45 AM","Insp Point Identification":"20200925|093038|","Work center":"NLEPACK2","Operation Description":"NPL 2@ Every 4Hr","Short Text Insp Char":"COMFONPCK Check","Target Value":"","Upper Tol Limit":"","Lower Tol Limit":"","Attribute":"","Unit of Measure":"","Char Valuation":"A","Code Catalog":"001","Code Description":"OK","User ID result entry":"USERNAME4","QT Result":"OK"},
{"Order":"88888888","Inspection Lot":"22222222222","Material":"11111111","Material Description":"Noodles 2 Min","Date Result entry":"09/25/2020","Time result entry":"01:49:27 PM","Insp Point Identification":"20200925|134921|","Work center":"NLEPACK2","Operation Description":"NPL 2@ Every 4Hr","Short Text Insp Char":"COMFONPCK Check","Target Value":"","Upper Tol Limit":"","Lower Tol Limit":"","Attribute":"","Unit of Measure":"","Char Valuation":"A","Code Catalog":"001","Code Description":"OK","User ID result entry":"USERNAME2","QT Result":"OK"},
{"Order":"88888888","Inspection Lot":"22222222222","Material":"11111111","Material Description":"Noodles 2 Min","Date Result entry":"09/25/2020","Time result entry":"05:27:00 PM","Insp Point Identification":"20200925|172654|","Work center":"NLEPACK2","Operation Description":"NPL 2@ Every 4Hr","Short Text Insp Char":"COMFONPCK Check","Target Value":"","Upper Tol Limit":"","Lower Tol Limit":"","Attribute":"","Unit of Measure":"","Char Valuation":"R","Code Catalog":"001","Code Description":"OK","User ID result entry":"USERNAME2","QT Result":"OK"},
{"Order":"88888888","Inspection Lot":"22222222222","Material":"11111111","Material Description":"Noodles 2 Min","Date Result entry":"09/25/2020","Time result entry":"09:26:33 PM","Insp Point Identification":"20200925|212630|","Work center":"NLEPACK2","Operation Description":"NPL 2@ Every 4Hr","Short Text Insp Char":"COMFONPCK Check","Target Value":"","Upper Tol Limit":"","Lower Tol Limit":"","Attribute":"","Unit of Measure":"","Char Valuation":"A","Code Catalog":"001","Code Description":"OK","User ID result entry":"USERNAME3","QT Result":"OK"},
{"Order":"88888888","Inspection Lot":"22222222222","Material":"11111111","Material Description":"Noodles 2 Min","Date Result entry":"09/25/2020","Time result entry":"04:44:00 AM","Insp Point Identification":"20200925|044358|","Work center":"NLEPACK2","Operation Description":"NPL 2@ Start Up of Productio","Short Text Insp Char":"COMFONPCK Check","Target Value":"","Upper Tol Limit":"","Lower Tol Limit":"","Attribute":"","Unit of Measure":"","Char Valuation":"A","Code Catalog":"001","Code Description":"OK","User ID result entry":"USERNAME1","QT Result":"NOK"},
{"Order":"88888888","Inspection Lot":"22222222222","Material":"11111111","Material Description":"Noodles 2 Min","Date Result entry":"09/26/2020","Time result entry":"01:36:45 AM","Insp Point Identification":"20200926|013517|","Work center":"NLEPACK2","Operation Description":"NPL 2@ Every 4Hr","Short Text Insp Char":"COMFONSHI Check","Target Value":"","Upper Tol Limit":"","Lower Tol Limit":"","Attribute":"","Unit of Measure":"","Char Valuation":"A","Code Catalog":"001","Code Description":"OK","User ID result entry":"USERNAME5","QT Result":"NOK"},
{"Order":"88888888","Inspection Lot":"22222222222","Material":"11111111","Material Description":"Noodles 2 Min","Date Result entry":"09/25/2020","Time result entry":"09:30:45 AM","Insp Point Identification":"20200925|093038|","Work center":"NLEPACK2","Operation Description":"NPL 2@ Every 4Hr","Short Text Insp Char":"COMFONSHI Check","Target Value":"","Upper Tol Limit":"","Lower Tol Limit":"","Attribute":"","Unit of Measure":"","Char Valuation":"A","Code Catalog":"001","Code Description":"OK","User ID result entry":"USERNAME4","QT Result":"NOK"},
{"Order":"88888888","Inspection Lot":"22222222222","Material":"11111111","Material Description":"Noodles 2 Min","Date Result entry":"09/25/2020","Time result entry":"01:49:27 PM","Insp Point Identification":"20200925|134921|","Work center":"NLEPACK2","Operation Description":"NPL 2@ Every 4Hr","Short Text Insp Char":"COMFONSHI Check","Target Value":"","Upper Tol Limit":"","Lower Tol Limit":"","Attribute":"","Unit of Measure":"","Char Valuation":"A","Code Catalog":"001","Code Description":"OK","User ID result entry":"USERNAME2","QT Result":"NOK"},
{"Order":"88888888","Inspection Lot":"22222222222","Material":"11111111","Material Description":"Noodles 2 Min","Date Result entry":"09/25/2020","Time result entry":"05:27:00 PM","Insp Point Identification":"20200925|172654|","Work center":"NLEPACK2","Operation Description":"NPL 2@ Every 4Hr","Short Text Insp Char":"COMFONSHI Check","Target Value":"","Upper Tol Limit":"","Lower Tol Limit":"","Attribute":"","Unit of Measure":"","Char Valuation":"A","Code Catalog":"001","Code Description":"OK","User ID result entry":"USERNAME2","QT Result":"NOK"},
{"Order":"88888888","Inspection Lot":"22222222222","Material":"11111111","Material Description":"Noodles 2 Min","Date Result entry":"09/25/2020","Time result entry":"09:26:34 PM","Insp Point Identification":"20200925|212630|","Work center":"NLEPACK2","Operation Description":"NPL 2@ Every 4Hr","Short Text Insp Char":"COMFONSHI Check","Target Value":"","Upper Tol Limit":"","Lower Tol Limit":"","Attribute":"","Unit of Measure":"","Char Valuation":"A","Code Catalog":"001","Code Description":"OK","User ID result entry":"USERNAME3","QT Result":"NOK"},
{"Order":"88888888","Inspection Lot":"22222222222","Material":"11111111","Material Description":"Noodles 2 Min","Date Result entry":"09/25/2020","Time result entry":"04:44:01 AM","Insp Point Identification":"20200925|044358|","Work center":"NLEPACK2","Operation Description":"NPL 2@ Start Up of Productio","Short Text Insp Char":"COMFONSHI Check","Target Value":"","Upper Tol Limit":"","Lower Tol Limit":"","Attribute":"","Unit of Measure":"","Char Valuation":"A","Code Catalog":"001","Code Description":"OK","User ID result entry":"USERNAME1","QT Result":"OK"},
{"Order":"88888888","Inspection Lot":"22222222222","Material":"11111111","Material Description":"Noodles 2 Min","Date Result entry":"09/26/2020","Time result entry":"04:30:21 AM","Insp Point Identification":"20200926|043017|","Work center":"NLEPACK2","Operation Description":"NPL 2@ End of Production","Short Text Insp Char":"CRT Check","Target Value":"","Upper Tol Limit":"","Lower Tol Limit":"","Attribute":"","Unit of Measure":"","Char Valuation":"A","Code Catalog":"001","Code Description":"OK","User ID result entry":"USERNAME3","QT Result":"OK"},
{"Order":"88888888","Inspection Lot":"22222222222","Material":"11111111","Material Description":"Noodles 2 Min","Date Result entry":"09/26/2020","Time result entry":"04:30:25 AM","Insp Point Identification":"20200926|043017|","Work center":"NLEPACK2","Operation Description":"NPL 2@ End of Production","Short Text Insp Char":"LMTCRCT Check","Target Value":"","Upper Tol Limit":"","Lower Tol Limit":"","Attribute":"","Unit of Measure":"","Char Valuation":"A","Code Catalog":"001","Code Description":"OK","User ID result entry":"USERNAME3","QT Result":"NOK"},
{"Order":"88888888","Inspection Lot":"22222222222","Material":"11111111","Material Description":"Noodles 2 Min","Date Result entry":"09/26/2020","Time result entry":"04:30:23 AM","Insp Point Identification":"20200926|043017|","Work center":"NLEPACK2","Operation Description":"NPL 2@ End of Production","Short Text Insp Char":"MOPDCTOR check","Target Value":"","Upper Tol Limit":"","Lower Tol Limit":"","Attribute":"","Unit of Measure":"","Char Valuation":"A","Code Catalog":"001","Code Description":"OK","User ID result entry":"USERNAME3","QT Result":"OK"},
{"Order":"88888888","Inspection Lot":"22222222222","Material":"11111111","Material Description":"Noodles 2 Min","Date Result entry":"09/26/2020","Time result entry":"01:36:45 AM","Insp Point Identification":"20200926|013517|","Work center":"NLEPACK2","Operation Description":"NPL 2@ Every 4Hr","Short Text Insp Char":"PCKSL Check","Target Value":"","Upper Tol Limit":"","Lower Tol Limit":"","Attribute":"","Unit of Measure":"","Char Valuation":"R","Code Catalog":"001","Code Description":"OK","User ID result entry":"USERNAME5","QT Result":"NOK"},
{"Order":"88888888","Inspection Lot":"22222222222","Material":"11111111","Material Description":"Noodles 2 Min","Date Result entry":"09/25/2020","Time result entry":"09:30:45 AM","Insp Point Identification":"20200925|093038|","Work center":"NLEPACK2","Operation Description":"NPL 2@ Every 4Hr","Short Text Insp Char":"PCKSL Check","Target Value":"","Upper Tol Limit":"","Lower Tol Limit":"","Attribute":"","Unit of Measure":"","Char Valuation":"A","Code Catalog":"001","Code Description":"OK","User ID result entry":"USERNAME4","QT Result":"NOK"},
{"Order":"88888888","Inspection Lot":"22222222222","Material":"11111111","Material Description":"Noodles 2 Min","Date Result entry":"09/25/2020","Time result entry":"01:49:27 PM","Insp Point Identification":"20200925|134921|","Work center":"NLEPACK2","Operation Description":"NPL 2@ Every 4Hr","Short Text Insp Char":"PCKSL Check","Target Value":"","Upper Tol Limit":"","Lower Tol Limit":"","Attribute":"","Unit of Measure":"","Char Valuation":"A","Code Catalog":"001","Code Description":"OK","User ID result entry":"USERNAME2","QT Result":"NOK"},
{"Order":"88888888","Inspection Lot":"22222222222","Material":"11111111","Material Description":"Noodles 2 Min","Date Result entry":"09/25/2020","Time result entry":"05:27:00 PM","Insp Point Identification":"20200925|172654|","Work center":"NLEPACK2","Operation Description":"NPL 2@ Every 4Hr","Short Text Insp Char":"PCKSL Check","Target Value":"","Upper Tol Limit":"","Lower Tol Limit":"","Attribute":"","Unit of Measure":"","Char Valuation":"A","Code Catalog":"001","Code Description":"OK","User ID result entry":"USERNAME2","QT Result":"NOK"},
{"Order":"88888888","Inspection Lot":"22222222222","Material":"11111111","Material Description":"Noodles 2 Min","Date Result entry":"09/25/2020","Time result entry":"09:26:36 PM","Insp Point Identification":"20200925|212630|","Work center":"NLEPACK2","Operation Description":"NPL 2@ Every 4Hr","Short Text Insp Char":"PCKSL Check","Target Value":"","Upper Tol Limit":"","Lower Tol Limit":"","Attribute":"","Unit of Measure":"","Char Valuation":"A","Code Catalog":"001","Code Description":"OK","User ID result entry":"USERNAME3","QT Result":"NOK"},
{"Order":"88888888","Inspection Lot":"22222222222","Material":"11111111","Material Description":"Noodles 2 Min","Date Result entry":"09/25/2020","Time result entry":"04:44:03 AM","Insp Point Identification":"20200925|044358|","Work center":"NLEPACK2","Operation Description":"NPL 2@ Start Up of Productio","Short Text Insp Char":"PCKSL Check","Target Value":"","Upper Tol Limit":"","Lower Tol Limit":"","Attribute":"","Unit of Measure":"","Char Valuation":"A","Code Catalog":"001","Code Description":"OK","User ID result entry":"USERNAME1","QT Result":"OK"},
{"Order":"88888888","Inspection Lot":"22222222222","Material":"11111111","Material Description":"Noodles 2 Min","Date Result entry":"09/26/2020","Time result entry":"04:30:37 AM","Insp Point Identification":"20200926|043034|","Work center":"NLEPACK2","Operation Description":"NPL 2@ End of each Batch","Short Text Insp Char":"SDAW Check","Target Value":"","Upper Tol Limit":"","Lower Tol Limit":"","Attribute":"","Unit of Measure":"","Char Valuation":"A","Code Catalog":"001","Code Description":"OK","User ID result entry":"USERNAME3","QT Result":"NOK"},
{"Order":"88888888","Inspection Lot":"22222222222","Material":"11111111","Material Description":"Noodles 2 Min","Date Result entry":"09/25/2020","Time result entry":"01:49:51 PM","Insp Point Identification":"20200925|134946|","Work center":"NLEPACK2","Operation Description":"NPL 2@ End of each Batch","Short Text Insp Char":"SDAW Check","Target Value":"","Upper Tol Limit":"","Lower Tol Limit":"","Attribute":"","Unit of Measure":"","Char Valuation":"A","Code Catalog":"001","Code Description":"OK","User ID result entry":"USERNAME2","QT Result":"OK"},
{"Order":"88888888","Inspection Lot":"22222222222","Material":"11111111","Material Description":"Noodles 2 Min","Date Result entry":"09/26/2020","Time result entry":"01:36:45 AM","Insp Point Identification":"20200926|013517|","Work center":"NLEPACK2","Operation Description":"NPL 2@ Every 4Hr","Short Text Insp Char":"SDECT Check","Target Value":"","Upper Tol Limit":"","Lower Tol Limit":"","Attribute":"","Unit of Measure":"","Char Valuation":"A","Code Catalog":"001","Code Description":"OK","User ID result entry":"USERNAME5","QT Result":"OK"},
{"Order":"88888888","Inspection Lot":"22222222222","Material":"11111111","Material Description":"Noodles 2 Min","Date Result entry":"09/25/2020","Time result entry":"09:30:45 AM","Insp Point Identification":"20200925|093038|","Work center":"NLEPACK2","Operation Description":"NPL 2@ Every 4Hr","Short Text Insp Char":"SDECT Check","Target Value":"","Upper Tol Limit":"","Lower Tol Limit":"","Attribute":"","Unit of Measure":"","Char Valuation":"A","Code Catalog":"001","Code Description":"OK","User ID result entry":"USERNAME4","QT Result":"OK"},
{"Order":"88888888","Inspection Lot":"22222222222","Material":"11111111","Material Description":"Noodles 2 Min","Date Result entry":"09/25/2020","Time result entry":"01:49:27 PM","Insp Point Identification":"20200925|134921|","Work center":"NLEPACK2","Operation Description":"NPL 2@ Every 4Hr","Short Text Insp Char":"SDECT Check","Target Value":"","Upper Tol Limit":"","Lower Tol Limit":"","Attribute":"","Unit of Measure":"","Char Valuation":"A","Code Catalog":"001","Code Description":"OK","User ID result entry":"USERNAME2","QT Result":"OK"},
{"Order":"88888888","Inspection Lot":"22222222222","Material":"11111111","Material Description":"Noodles 2 Min","Date Result entry":"09/25/2020","Time result entry":"05:27:00 PM","Insp Point Identification":"20200925|172654|","Work center":"NLEPACK2","Operation Description":"NPL 2@ Every 4Hr","Short Text Insp Char":"SDECT Check","Target Value":"","Upper Tol Limit":"","Lower Tol Limit":"","Attribute":"","Unit of Measure":"","Char Valuation":"R","Code Catalog":"001","Code Description":"OK","User ID result entry":"USERNAME2","QT Result":"OK"},
{"Order":"88888888","Inspection Lot":"22222222222","Material":"11111111","Material Description":"Noodles 2 Min","Date Result entry":"09/25/2020","Time result entry":"09:26:35 PM","Insp Point Identification":"20200925|212630|","Work center":"NLEPACK2","Operation Description":"NPL 2@ Every 4Hr","Short Text Insp Char":"SDECT Check","Target Value":"","Upper Tol Limit":"","Lower Tol Limit":"","Attribute":"","Unit of Measure":"","Char Valuation":"A","Code Catalog":"001","Code Description":"OK","User ID result entry":"USERNAME3","QT Result":"OK"},
{"Order":"88888888","Inspection Lot":"22222222222","Material":"11111111","Material Description":"Noodles 2 Min","Date Result entry":"09/25/2020","Time result entry":"04:44:02 AM","Insp Point Identification":"20200925|044358|","Work center":"NLEPACK2","Operation Description":"NPL 2@ Start Up of Productio","Short Text Insp Char":"SDECT Check","Target Value":"","Upper Tol Limit":"","Lower Tol Limit":"","Attribute":"","Unit of Measure":"","Char Valuation":"A","Code Catalog":"001","Code Description":"OK","User ID result entry":"USERNAME1","QT Result":"NOK"},
{"Order":"88888888","Inspection Lot":"22222222222","Material":"11111111","Material Description":"Noodles 2 Min","Date Result entry":"09/26/2020","Time result entry":"04:30:22 AM","Insp Point Identification":"20200926|043017|","Work center":"NLEPACK2","Operation Description":"NPL 2@ End of Production","Short Text Insp Char":"SDNTBLT Check","Target Value":"","Upper Tol Limit":"","Lower Tol Limit":"","Attribute":"","Unit of Measure":"","Char Valuation":"A","Code Catalog":"001","Code Description":"OK","User ID result entry":"USERNAME3","QT Result":"NOK"},
{"Order":"88888888","Inspection Lot":"22222222222","Material":"11111111","Material Description":"Noodles 2 Min","Date Result entry":"09/26/2020","Time result entry":"04:30:39 AM","Insp Point Identification":"20200926|043034|","Work center":"NLEPACK2","Operation Description":"NPL 2@ End of each Batch","Short Text Insp Char":"TRMONI Check","Target Value":"","Upper Tol Limit":"","Lower Tol Limit":"","Attribute":"","Unit of Measure":"","Char Valuation":"A","Code Catalog":"001","Code Description":"OK","User ID result entry":"USERNAME3","QT Result":"NOK"},
{"Order":"88888888","Inspection Lot":"22222222222","Material":"11111111","Material Description":"Noodles 2 Min","Date Result entry":"09/25/2020","Time result entry":"01:49:51 PM","Insp Point Identification":"20200925|134946|","Work center":"NLEPACK2","Operation Description":"NPL 2@ End of each Batch","Short Text Insp Char":"TRMONI Check","Target Value":"","Upper Tol Limit":"","Lower Tol Limit":"","Attribute":"","Unit of Measure":"","Char Valuation":"A","Code Catalog":"001","Code Description":"OK","User ID result entry":"USERNAME2","QT Result":"OK"},
{"Order":"88888888","Inspection Lot":"22222222222","Material":"11111111","Material Description":"Noodles 2 Min","Date Result entry":"09/26/2020","Time result entry":"04:30:24 AM","Insp Point Identification":"20200926|043017|","Work center":"NLEPACK2","Operation Description":"NPL 2@ End of Production","Short Text Insp Char":"WRPMR Check","Target Value":"","Upper Tol Limit":"","Lower Tol Limit":"","Attribute":"","Unit of Measure":"","Char Valuation":"A","Code Catalog":"001","Code Description":"OK","User ID result entry":"USERNAME3","QT Result":"OK"},
{"Order":"88888888","Inspection Lot":"22222222222","Material":"11111111","Material Description":"Noodles 2 Min","Date Result entry":"09/26/2020","Time result entry":"04:30:24 AM","Insp Point Identification":"20200926|043017|","Work center":"NLEPACK2","Operation Description":"NPL 2@ End of Production","Short Text Insp Char":"WRPTOKI Check","Target Value":"","Upper Tol Limit":"","Lower Tol Limit":"","Attribute":"","Unit of Measure":"","Char Valuation":"R","Code Catalog":"001","Code Description":"OK","User ID result entry":"USERNAME3","QT Result":"NOK"},
{"Order":"88888888","Inspection Lot":"22222222222","Material":"11111111","Material Description":"Noodles 2 Min","Date Result entry":"09/25/2020","Time result entry":"04:44:12 AM","Insp Point Identification":"20200925|044411|","Work center":"NLEPACK2","Operation Description":"NPL 2@Startup of batch","Short Text Insp Char":"WTTAR Check","Target Value":"","Upper Tol Limit":"","Lower Tol Limit":"","Attribute":"","Unit of Measure":"","Char Valuation":"A","Code Catalog":"001","Code Description":"OK","User ID result entry":"USERNAME1","QT Result":"OK"},
{"Order":"88888888","Inspection Lot":"22222222222","Material":"11111111","Material Description":"Noodles 2 Min","Date Result entry":"09/25/2020","Time result entry":"02:43:27 PM","Insp Point Identification":"20200925|144324|","Work center":"NLEPACK2","Operation Description":"NPL 2@Startup of batch","Short Text Insp Char":"WTTAR Check","Target Value":"","Upper Tol Limit":"","Lower Tol Limit":"","Attribute":"","Unit of Measure":"","Char Valuation":"A","Code Catalog":"001","Code Description":"OK","User ID result entry":"USERNAME2","QT Result":"NOK"},
{"Order":"88888888","Inspection Lot":"22222222222","Material":"11111111","Material Description":"Noodles 2 Min","Date Result entry":"09/25/2020","Time result entry":"04:43:44 AM","Insp Point Identification":"20200925|044342|","Work center":"NLEPACK5","Operation Description":"NPL5 @ Start up of Each Shift","Short Text Insp Char":"CAF Check","Target Value":"","Upper Tol Limit":"","Lower Tol Limit":"","Attribute":"","Unit of Measure":"","Char Valuation":"A","Code Catalog":"001","Code Description":"OK","User ID result entry":"USERNAME1","QT Result":"OK"},
{"Order":"88888888","Inspection Lot":"22222222222","Material":"11111111","Material Description":"Noodles 2 Min","Date Result entry":"09/25/2020","Time result entry":"02:43:47 PM","Insp Point Identification":"20200925|144336|","Work center":"NLEPACK5","Operation Description":"NPL5 @ Start up of Each Shift","Short Text Insp Char":"CAF Check","Target Value":"","Upper Tol Limit":"","Lower Tol Limit":"","Attribute":"","Unit of Measure":"","Char Valuation":"A","Code Catalog":"001","Code Description":"OK","User ID result entry":"USERNAME2","QT Result":"NOK"},
{"Order":"88888888","Inspection Lot":"22222222222","Material":"11111111","Material Description":"Noodles 2 Min","Date Result entry":"09/25/2020","Time result entry":"09:27:39 PM","Insp Point Identification":"20200925|212736|","Work center":"NLEPACK5","Operation Description":"NPL5 @ Start up of Each Shift","Short Text Insp Char":"CAF Check","Target Value":"","Upper Tol Limit":"","Lower Tol Limit":"","Attribute":"","Unit of Measure":"","Char Valuation":"A","Code Catalog":"001","Code Description":"OK","User ID result entry":"USERNAME3","QT Result":"OK"},
{"Order":"88888888","Inspection Lot":"22222222222","Material":"11111111","Material Description":"Noodles 2 Min","Date Result entry":"09/25/2020","Time result entry":"04:43:45 AM","Insp Point Identification":"20200925|044342|","Work center":"NLEPACK5","Operation Description":"NPL5 @ Start up of Each Shift","Short Text Insp Char":"COMFONPCK Check","Target Value":"","Upper Tol Limit":"","Lower Tol Limit":"","Attribute":"","Unit of Measure":"","Char Valuation":"A","Code Catalog":"001","Code Description":"OK","User ID result entry":"USERNAME1","QT Result":"NOK"},
{"Order":"88888888","Inspection Lot":"22222222222","Material":"11111111","Material Description":"Noodles 2 Min","Date Result entry":"09/25/2020","Time result entry":"02:43:47 PM","Insp Point Identification":"20200925|144336|","Work center":"NLEPACK5","Operation Description":"NPL5 @ Start up of Each Shift","Short Text Insp Char":"COMFONPCK Check","Target Value":"","Upper Tol Limit":"","Lower Tol Limit":"","Attribute":"","Unit of Measure":"","Char Valuation":"A","Code Catalog":"001","Code Description":"OK","User ID result entry":"USERNAME2","QT Result":"OK"},
{"Order":"88888888","Inspection Lot":"22222222222","Material":"11111111","Material Description":"Noodles 2 Min","Date Result entry":"09/25/2020","Time result entry":"09:27:43 PM","Insp Point Identification":"20200925|212736|","Work center":"NLEPACK5","Operation Description":"NPL5 @ Start up of Each Shift","Short Text Insp Char":"COMFONPCK Check","Target Value":"","Upper Tol Limit":"","Lower Tol Limit":"","Attribute":"","Unit of Measure":"","Char Valuation":"A","Code Catalog":"001","Code Description":"OK","User ID result entry":"USERNAME3","QT Result":"NOK"},
{"Order":"88888888","Inspection Lot":"22222222222","Material":"11111111","Material Description":"Noodles 2 Min","Date Result entry":"09/25/2020","Time result entry":"04:43:46 AM","Insp Point Identification":"20200925|044342|","Work center":"NLEPACK5","Operation Description":"NPL5 @ Start up of Each Shift","Short Text Insp Char":"COMFONSHI Check","Target Value":"","Upper Tol Limit":"","Lower Tol Limit":"","Attribute":"","Unit of Measure":"","Char Valuation":"R","Code Catalog":"001","Code Description":"OK","User ID result entry":"USERNAME1","QT Result":"OK"},
{"Order":"88888888","Inspection Lot":"22222222222","Material":"11111111","Material Description":"Noodles 2 Min","Date Result entry":"09/25/2020","Time result entry":"02:43:47 PM","Insp Point Identification":"20200925|144336|","Work center":"NLEPACK5","Operation Description":"NPL5 @ Start up of Each Shift","Short Text Insp Char":"COMFONSHI Check","Target Value":"","Upper Tol Limit":"","Lower Tol Limit":"","Attribute":"","Unit of Measure":"","Char Valuation":"A","Code Catalog":"001","Code Description":"OK","User ID result entry":"USERNAME2","QT Result":"NOK"},
{"Order":"88888888","Inspection Lot":"22222222222","Material":"11111111","Material Description":"Noodles 2 Min","Date Result entry":"09/25/2020","Time result entry":"09:27:44 PM","Insp Point Identification":"20200925|212736|","Work center":"NLEPACK5","Operation Description":"NPL5 @ Start up of Each Shift","Short Text Insp Char":"COMFONSHI Check","Target Value":"","Upper Tol Limit":"","Lower Tol Limit":"","Attribute":"","Unit of Measure":"","Char Valuation":"A","Code Catalog":"001","Code Description":"OK","User ID result entry":"USERNAME3","QT Result":"OK"},
{"Order":"88888888","Inspection Lot":"22222222222","Material":"11111111","Material Description":"Noodles 2 Min","Date Result entry":"09/26/2020","Time result entry":"01:37:18 AM","Insp Point Identification":"20200926|013715|","Work center":"NLEPACK5","Operation Description":"DTMDL @ Every 4hr","Short Text Insp Char":"MOPDCTOR check","Target Value":"","Upper Tol Limit":"","Lower Tol Limit":"","Attribute":"","Unit of Measure":"","Char Valuation":"A","Code Catalog":"001","Code Description":"Ok","User ID result entry":"USERNAME5","QT Result":"OK"},
{"Order":"88888888","Inspection Lot":"22222222222","Material":"11111111","Material Description":"Noodles 2 Min","Date Result entry":"09/25/2020","Time result entry":"09:30:55 AM","Insp Point Identification":"20200925|093050|","Work center":"NLEPACK5","Operation Description":"DTMDL @ Every 4hr","Short Text Insp Char":"MOPDCTOR check","Target Value":"","Upper Tol Limit":"","Lower Tol Limit":"","Attribute":"","Unit of Measure":"","Char Valuation":"A","Code Catalog":"001","Code Description":"Ok","User ID result entry":"USERNAME4","QT Result":"OK"},
{"Order":"88888888","Inspection Lot":"22222222222","Material":"11111111","Material Description":"Noodles 2 Min","Date Result entry":"09/25/2020","Time result entry":"05:26:47 PM","Insp Point Identification":"20200925|172644|","Work center":"NLEPACK5","Operation Description":"DTMDL @ Every 4hr","Short Text Insp Char":"MOPDCTOR check","Target Value":"","Upper Tol Limit":"","Lower Tol Limit":"","Attribute":"","Unit of Measure":"","Char Valuation":"A","Code Catalog":"001","Code Description":"Ok","User ID result entry":"USERNAME2","QT Result":"NOK"},
{"Order":"88888887","Inspection Lot":"22222222222","Material":"11111111","Material Description":"Noodles 2 Min","Date Result entry":"09/25/2020","Time result entry":"02:43:47 PM","Insp Point Identification":"20200925|144336|","Work center":"NLEPACK5","Operation Description":"NPL5 @ Start up of Each Shift","Short Text Insp Char":"MOPDCTOR check","Target Value":"","Upper Tol Limit":"","Lower Tol Limit":"","Attribute":"","Unit of Measure":"","Char Valuation":"A","Code Catalog":"001","Code Description":"OK","User ID result entry":"USERNAME2","QT Result":"NOK"},
{"Order":"88888888","Inspection Lot":"22222222222","Material":"11111111","Material Description":"Noodles 2 Min","Date Result entry":"09/25/2020","Time result entry":"04:43:50 AM","Insp Point Identification":"20200925|044342|","Work center":"NLEPACK5","Operation Description":"NPL5 @ Start up of Each Shift","Short Text Insp Char":"MOPDCTOR check","Target Value":"","Upper Tol Limit":"","Lower Tol Limit":"","Attribute":"","Unit of Measure":"","Char Valuation":"A","Code Catalog":"001","Code Description":"OK","User ID result entry":"USERNAME1","QT Result":"OK"},
{"Order":"88888888","Inspection Lot":"22222222222","Material":"11111111","Material Description":"Noodles 2 Min","Date Result entry":"09/25/2020","Time result entry":"09:27:48 PM","Insp Point Identification":"20200925|212736|","Work center":"NLEPACK5","Operation Description":"NPL5 @ Start up of Each Shift","Short Text Insp Char":"MOPDCTOR check","Target Value":"","Upper Tol Limit":"","Lower Tol Limit":"","Attribute":"","Unit of Measure":"","Char Valuation":"A","Code Catalog":"001","Code Description":"OK","User ID result entry":"USERNAME3","QT Result":"OK"},
{"Order":"88888888","Inspection Lot":"22222222222","Material":"11111111","Material Description":"Noodles 2 Min","Date Result entry":"09/25/2020","Time result entry":"04:43:48 AM","Insp Point Identification":"20200925|044342|","Work center":"NLEPACK5","Operation Description":"NPL5 @ Start up of Each Shift","Short Text Insp Char":"PCKSL Check","Target Value":"","Upper Tol Limit":"","Lower Tol Limit":"","Attribute":"","Unit of Measure":"","Char Valuation":"A","Code Catalog":"001","Code Description":"OK","User ID result entry":"USERNAME1","QT Result":"OK"},
{"Order":"88888888","Inspection Lot":"22222222222","Material":"11111111","Material Description":"Noodles 2 Min","Date Result entry":"09/25/2020","Time result entry":"02:43:47 PM","Insp Point Identification":"20200925|144336|","Work center":"NLEPACK5","Operation Description":"NPL5 @ Start up of Each Shift","Short Text Insp Char":"PCKSL Check","Target Value":"","Upper Tol Limit":"","Lower Tol Limit":"","Attribute":"","Unit of Measure":"","Char Valuation":"A","Code Catalog":"001","Code Description":"OK","User ID result entry":"USERNAME2","QT Result":"NOK"},
{"Order":"88888888","Inspection Lot":"22222222222","Material":"11111111","Material Description":"Noodles 2 Min","Date Result entry":"09/25/2020","Time result entry":"09:27:46 PM","Insp Point Identification":"20200925|212736|","Work center":"NLEPACK5","Operation Description":"NPL5 @ Start up of Each Shift","Short Text Insp Char":"PCKSL Check","Target Value":"","Upper Tol Limit":"","Lower Tol Limit":"","Attribute":"","Unit of Measure":"","Char Valuation":"A","Code Catalog":"001","Code Description":"OK","User ID result entry":"USERNAME3","QT Result":"OK"},
{"Order":"88888888","Inspection Lot":"22222222222","Material":"11111111","Material Description":"Noodles 2 Min","Date Result entry":"09/25/2020","Time result entry":"04:43:47 AM","Insp Point Identification":"20200925|044342|","Work center":"NLEPACK5","Operation Description":"NPL5 @ Start up of Each Shift","Short Text Insp Char":"SDECT Check","Target Value":"","Upper Tol Limit":"","Lower Tol Limit":"","Attribute":"","Unit of Measure":"","Char Valuation":"R","Code Catalog":"001","Code Description":"OK","User ID result entry":"USERNAME1","QT Result":"NOK"},
{"Order":"88888888","Inspection Lot":"22222222222","Material":"11111111","Material Description":"Noodles 2 Min","Date Result entry":"09/25/2020","Time result entry":"02:43:47 PM","Insp Point Identification":"20200925|144336|","Work center":"NLEPACK5","Operation Description":"NPL5 @ Start up of Each Shift","Short Text Insp Char":"SDECT Check","Target Value":"","Upper Tol Limit":"","Lower Tol Limit":"","Attribute":"","Unit of Measure":"","Char Valuation":"A","Code Catalog":"001","Code Description":"OK","User ID result entry":"USERNAME2","QT Result":"OK"},
{"Order":"88888888","Inspection Lot":"22222222222","Material":"11111111","Material Description":"Noodles 2 Min","Date Result entry":"09/25/2020","Time result entry":"09:27:45 PM","Insp Point Identification":"20200925|212736|","Work center":"NLEPACK5","Operation Description":"NPL5 @ Start up of Each Shift","Short Text Insp Char":"SDECT Check","Target Value":"","Upper Tol Limit":"","Lower Tol Limit":"","Attribute":"","Unit of Measure":"","Char Valuation":"A","Code Catalog":"001","Code Description":"OK","User ID result entry":"USERNAME3","QT Result":"NOK"},
{"Order":"88888888","Inspection Lot":"22222222222","Material":"11111111","Material Description":"Noodles 2 Min","Date Result entry":"09/25/2020","Time result entry":"04:43:49 AM","Insp Point Identification":"20200925|044342|","Work center":"NLEPACK5","Operation Description":"NPL5 @ Start up of Each Shift","Short Text Insp Char":"SDNTBLT Check","Target Value":"","Upper Tol Limit":"","Lower Tol Limit":"","Attribute":"","Unit of Measure":"","Char Valuation":"A","Code Catalog":"001","Code Description":"OK","User ID result entry":"USERNAME1","QT Result":"NOK"},
{"Order":"88888888","Inspection Lot":"22222222222","Material":"11111111","Material Description":"Noodles 2 Min","Date Result entry":"09/25/2020","Time result entry":"02:43:47 PM","Insp Point Identification":"20200925|144336|","Work center":"NLEPACK5","Operation Description":"NPL5 @ Start up of Each Shift","Short Text Insp Char":"SDNTBLT Check","Target Value":"","Upper Tol Limit":"","Lower Tol Limit":"","Attribute":"","Unit of Measure":"","Char Valuation":"A","Code Catalog":"001","Code Description":"OK","User ID result entry":"USERNAME2","QT Result":"OK"},
{"Order":"88888888","Inspection Lot":"22222222222","Material":"11111111","Material Description":"Noodles 2 Min","Date Result entry":"09/25/2020","Time result entry":"09:27:47 PM","Insp Point Identification":"20200925|212736|","Work center":"NLEPACK5","Operation Description":"NPL5 @ Start up of Each Shift","Short Text Insp Char":"SDNTBLT Check","Target Value":"","Upper Tol Limit":"","Lower Tol Limit":"","Attribute":"","Unit of Measure":"","Char Valuation":"A","Code Catalog":"001","Code Description":"OK","User ID result entry":"USERNAME3","QT Result":"NOK"},
{"Order":"88888888","Inspection Lot":"22222222222","Material":"11111111","Material Description":"Noodles 2 Min","Date Result entry":"09/25/2020","Time result entry":"04:43:52 AM","Insp Point Identification":"20200925|044342|","Work center":"NLEPACK5","Operation Description":"NPL5 @ Start up of Each Shift","Short Text Insp Char":"WRPMR Check","Target Value":"","Upper Tol Limit":"","Lower Tol Limit":"","Attribute":"","Unit of Measure":"","Char Valuation":"A","Code Catalog":"001","Code Description":"OK","User ID result entry":"USERNAME1","QT Result":"OK"},
{"Order":"88888888","Inspection Lot":"22222222222","Material":"11111111","Material Description":"Noodles 2 Min","Date Result entry":"09/25/2020","Time result entry":"02:43:47 PM","Insp Point Identification":"20200925|144336|","Work center":"NLEPACK5","Operation Description":"NPL5 @ Start up of Each Shift","Short Text Insp Char":"WRPMR Check","Target Value":"","Upper Tol Limit":"","Lower Tol Limit":"","Attribute":"","Unit of Measure":"","Char Valuation":"A","Code Catalog":"001","Code Description":"OK","User ID result entry":"USERNAME2","QT Result":"NOK"},
{"Order":"88888888","Inspection Lot":"22222222222","Material":"11111111","Material Description":"Noodles 2 Min","Date Result entry":"09/25/2020","Time result entry":"09:27:50 PM","Insp Point Identification":"20200925|212736|","Work center":"NLEPACK5","Operation Description":"NPL5 @ Start up of Each Shift","Short Text Insp Char":"WRPMR Check","Target Value":"","Upper Tol Limit":"","Lower Tol Limit":"","Attribute":"","Unit of Measure":"","Char Valuation":"A","Code Catalog":"001","Code Description":"OK","User ID result entry":"USERNAME3","QT Result":"OK"},
{"Order":"88888888","Inspection Lot":"22222222222","Material":"11111111","Material Description":"Noodles 2 Min","Date Result entry":"09/25/2020","Time result entry":"04:43:51 AM","Insp Point Identification":"20200925|044342|","Work center":"NLEPACK5","Operation Description":"NPL5 @ Start up of Each Shift","Short Text Insp Char":"WRPTOKI Check","Target Value":"","Upper Tol Limit":"","Lower Tol Limit":"","Attribute":"","Unit of Measure":"","Char Valuation":"R","Code Catalog":"001","Code Description":"OK","User ID result entry":"USERNAME1","QT Result":"NOK"},
{"Order":"88888888","Inspection Lot":"22222222222","Material":"11111111","Material Description":"Noodles 2 Min","Date Result entry":"09/25/2020","Time result entry":"02:43:47 PM","Insp Point Identification":"20200925|144336|","Work center":"NLEPACK5","Operation Description":"NPL5 @ Start up of Each Shift","Short Text Insp Char":"WRPTOKI Check","Target Value":"","Upper Tol Limit":"","Lower Tol Limit":"","Attribute":"","Unit of Measure":"","Char Valuation":"A","Code Catalog":"001","Code Description":"OK","User ID result entry":"USERNAME2","QT Result":"OK"},
{"Order":"88879877","Inspection Lot":"22222222222","Material":"11111111","Material Description":"Noodles 2 Min","Date Result entry":"09/25/2020","Time result entry":"09:27:49 PM","Insp Point Identification":"20200925|212736|","Work center":"NLEPACK5","Operation Description":"NPL5 @ Start up of Each Shift","Short Text Insp Char":"WRPTOKI Check","Target Value":"","Upper Tol Limit":"","Lower Tol Limit":"","Attribute":"","Unit of Measure":"","Char Valuation":"A","Code Catalog":"001","Code Description":"OK","User ID result entry":"USERNAME3","QT Result":"NOK"},
{"Order":"88879877","Inspection Lot":"22222222222","Material":"11111111","Material Description":"Noodles 2 Min","Date Result entry":"09/27/2020","Time result entry":"02:37:18 AM","Insp Point Identification":"20200926|013715|","Work center":"NLEPACK6","Operation Description":"DTMDL @ Every 4hr","Short Text Insp Char":"MOPDCTOR check","Target Value":"","Upper Tol Limit":"","Lower Tol Limit":"","Attribute":"","Unit of Measure":"","Char Valuation":"A","Code Catalog":"002","Code Description":"Ok","User ID result entry":"USERNAME6","QT Result":"NOK"},
{"Order":"88879877","Inspection Lot":"22222222222","Material":"11111111","Material Description":"Noodles 2 Min","Date Result entry":"09/25/2020","Time result entry":"04:43:50 AM","Insp Point Identification":"20200925|044342|","Work center":"NLEPACK5","Operation Description":"NPL5 @ Start up of Each Shift","Short Text Insp Char":"MOPDCTOR check","Target Value":"","Upper Tol Limit":"","Lower Tol Limit":"","Attribute":"","Unit of Measure":"","Char Valuation":"A","Code Catalog":"001","Code Description":"OK","User ID result entry":"USERNAME1","QT Result":"OK"},
{"Order":"88879877","Inspection Lot":"22222222222","Material":"11111111","Material Description":"Noodles 2 Min","Date Result entry":"09/25/2020","Time result entry":"09:27:48 PM","Insp Point Identification":"20200925|212736|","Work center":"NLEPACK5","Operation Description":"NPL5 @ Start up of Each Shift","Short Text Insp Char":"MOPDCTOR check","Target Value":"","Upper Tol Limit":"","Lower Tol Limit":"","Attribute":"","Unit of Measure":"","Char Valuation":"A","Code Catalog":"001","Code Description":"OK","User ID result entry":"USERNAME3","QT Result":"OK"},
{"Order":"88879877","Inspection Lot":"22222222222","Material":"11111111","Material Description":"Noodles 2 Min","Date Result entry":"09/25/2020","Time result entry":"04:43:48 AM","Insp Point Identification":"20200925|044342|","Work center":"NLEPACK5","Operation Description":"NPL5 @ Start up of Each Shift","Short Text Insp Char":"PCKSL Check","Target Value":"","Upper Tol Limit":"","Lower Tol Limit":"","Attribute":"","Unit of Measure":"","Char Valuation":"A","Code Catalog":"001","Code Description":"OK","User ID result entry":"USERNAME1","QT Result":"OK"},
{"Order":"88879877","Inspection Lot":"22222222222","Material":"11111111","Material Description":"Noodles 2 Min","Date Result entry":"09/25/2020","Time result entry":"02:43:47 PM","Insp Point Identification":"20200925|144336|","Work center":"NLEPACK5","Operation Description":"NPL5 @ Start up of Each Shift","Short Text Insp Char":"PCKSL Check","Target Value":"","Upper Tol Limit":"","Lower Tol Limit":"","Attribute":"","Unit of Measure":"","Char Valuation":"A","Code Catalog":"001","Code Description":"OK","User ID result entry":"USERNAME2","QT Result":"NOK"},
{"Order":"88879877","Inspection Lot":"22222222222","Material":"11111111","Material Description":"Noodles 2 Min","Date Result entry":"09/25/2020","Time result entry":"09:27:46 PM","Insp Point Identification":"20200925|212736|","Work center":"NLEPACK5","Operation Description":"NPL5 @ Start up of Each Shift","Short Text Insp Char":"PCKSL Check","Target Value":"","Upper Tol Limit":"","Lower Tol Limit":"","Attribute":"","Unit of Measure":"","Char Valuation":"A","Code Catalog":"001","Code Description":"OK","User ID result entry":"USERNAME3","QT Result":"OK"},
{"Order":"88879877","Inspection Lot":"22222222222","Material":"11111111","Material Description":"Noodles 2 Min","Date Result entry":"09/25/2020","Time result entry":"04:43:47 AM","Insp Point Identification":"20200925|044342|","Work center":"NLEPACK5","Operation Description":"NPL5 @ Start up of Each Shift","Short Text Insp Char":"SDECT Check","Target Value":"","Upper Tol Limit":"","Lower Tol Limit":"","Attribute":"","Unit of Measure":"","Char Valuation":"R","Code Catalog":"001","Code Description":"OK","User ID result entry":"USERNAME1","QT Result":"NOK"},
{"Order":"88879877","Inspection Lot":"22222222222","Material":"11111111","Material Description":"Noodles 2 Min","Date Result entry":"09/25/2020","Time result entry":"02:43:47 PM","Insp Point Identification":"20200925|144336|","Work center":"NLEPACK5","Operation Description":"NPL5 @ Start up of Each Shift","Short Text Insp Char":"SDECT Check","Target Value":"","Upper Tol Limit":"","Lower Tol Limit":"","Attribute":"","Unit of Measure":"","Char Valuation":"A","Code Catalog":"001","Code Description":"OK","User ID result entry":"USERNAME2","QT Result":"OK"},
{"Order":"88879877","Inspection Lot":"22222222222","Material":"11111111","Material Description":"Noodles 2 Min","Date Result entry":"09/25/2020","Time result entry":"09:27:45 PM","Insp Point Identification":"20200925|212736|","Work center":"NLEPACK5","Operation Description":"NPL5 @ Start up of Each Shift","Short Text Insp Char":"SDECT Check","Target Value":"","Upper Tol Limit":"","Lower Tol Limit":"","Attribute":"","Unit of Measure":"","Char Valuation":"A","Code Catalog":"001","Code Description":"OK","User ID result entry":"USERNAME3","QT Result":"NOK"},
{"Order":"88879877","Inspection Lot":"22222222222","Material":"11111111","Material Description":"Noodles 2 Min","Date Result entry":"09/25/2020","Time result entry":"04:43:49 AM","Insp Point Identification":"20200925|044342|","Work center":"NLEPACK5","Operation Description":"NPL5 @ Start up of Each Shift","Short Text Insp Char":"SDNTBLT Check","Target Value":"","Upper Tol Limit":"","Lower Tol Limit":"","Attribute":"","Unit of Measure":"","Char Valuation":"A","Code Catalog":"001","Code Description":"OK","User ID result entry":"USERNAME1","QT Result":"NOK"},
{"Order":"88879877","Inspection Lot":"22222222222","Material":"11111111","Material Description":"Noodles 2 Min","Date Result entry":"09/25/2020","Time result entry":"02:43:47 PM","Insp Point Identification":"20200925|144336|","Work center":"NLEPACK5","Operation Description":"NPL5 @ Start up of Each Shift","Short Text Insp Char":"SDNTBLT Check","Target Value":"","Upper Tol Limit":"","Lower Tol Limit":"","Attribute":"","Unit of Measure":"","Char Valuation":"A","Code Catalog":"001","Code Description":"OK","User ID result entry":"USERNAME2","QT Result":"OK"},
{"Order":"88879877","Inspection Lot":"22222222222","Material":"11111111","Material Description":"Noodles 2 Min","Date Result entry":"09/25/2020","Time result entry":"09:27:47 PM","Insp Point Identification":"20200925|212736|","Work center":"NLEPACK5","Operation Description":"NPL5 @ Start up of Each Shift","Short Text Insp Char":"SDNTBLT Check","Target Value":"","Upper Tol Limit":"","Lower Tol Limit":"","Attribute":"","Unit of Measure":"","Char Valuation":"A","Code Catalog":"001","Code Description":"OK","User ID result entry":"USERNAME3","QT Result":"NOK"},
{"Order":"88879877","Inspection Lot":"22222222222","Material":"11111111","Material Description":"Noodles 2 Min","Date Result entry":"09/25/2020","Time result entry":"04:43:52 AM","Insp Point Identification":"20200925|044342|","Work center":"NLEPACK5","Operation Description":"NPL5 @ Start up of Each Shift","Short Text Insp Char":"WRPMR Check","Target Value":"","Upper Tol Limit":"","Lower Tol Limit":"","Attribute":"","Unit of Measure":"","Char Valuation":"A","Code Catalog":"001","Code Description":"OK","User ID result entry":"USERNAME1","QT Result":"OK"},
{"Order":"88879877","Inspection Lot":"22222222222","Material":"11111111","Material Description":"Noodles 2 Min","Date Result entry":"09/25/2020","Time result entry":"02:43:47 PM","Insp Point Identification":"20200925|144336|","Work center":"NLEPACK5","Operation Description":"NPL5 @ Start up of Each Shift","Short Text Insp Char":"WRPMR Check","Target Value":"","Upper Tol Limit":"","Lower Tol Limit":"","Attribute":"","Unit of Measure":"","Char Valuation":"A","Code Catalog":"001","Code Description":"OK","User ID result entry":"USERNAME2","QT Result":"NOK"},
{"Order":"88879877","Inspection Lot":"22222222222","Material":"11111111","Material Description":"Noodles 2 Min","Date Result entry":"09/25/2020","Time result entry":"09:27:50 PM","Insp Point Identification":"20200925|212736|","Work center":"NLEPACK5","Operation Description":"NPL5 @ Start up of Each Shift","Short Text Insp Char":"WRPMR Check","Target Value":"","Upper Tol Limit":"","Lower Tol Limit":"","Attribute":"","Unit of Measure":"","Char Valuation":"A","Code Catalog":"001","Code Description":"OK","User ID result entry":"USERNAME3","QT Result":"OK"},
{"Order":"88879877","Inspection Lot":"22222222222","Material":"11111111","Material Description":"Noodles 2 Min","Date Result entry":"09/25/2020","Time result entry":"04:43:51 AM","Insp Point Identification":"20200925|044342|","Work center":"NLEPACK5","Operation Description":"NPL5 @ Start up of Each Shift","Short Text Insp Char":"WRPTOKI Check","Target Value":"","Upper Tol Limit":"","Lower Tol Limit":"","Attribute":"","Unit of Measure":"","Char Valuation":"R","Code Catalog":"001","Code Description":"OK","User ID result entry":"USERNAME1","QT Result":"NOK"},
{"Order":"88879877","Inspection Lot":"22222222222","Material":"11111111","Material Description":"Noodles 2 Min","Date Result entry":"09/25/2020","Time result entry":"02:43:47 PM","Insp Point Identification":"20200925|144336|","Work center":"NLEPACK5","Operation Description":"NPL5 @ Start up of Each Shift","Short Text Insp Char":"WRPTOKI Check","Target Value":"","Upper Tol Limit":"","Lower Tol Limit":"","Attribute":"","Unit of Measure":"","Char Valuation":"A","Code Catalog":"001","Code Description":"OK","User ID result entry":"USERNAME2","QT Result":"OK"},
{"Order":"88879877","Inspection Lot":"22222222222","Material":"11111111","Material Description":"Noodles 2 Min","Date Result entry":"09/25/2020","Time result entry":"09:27:49 PM","Insp Point Identification":"20200925|212736|","Work center":"NLEPACK5","Operation Description":"NPL5 @ Start up of Each Shift","Short Text Insp Char":"WRPTOKI Check","Target Value":"","Upper Tol Limit":"","Lower Tol Limit":"","Attribute":"","Unit of Measure":"","Char Valuation":"A","Code Catalog":"001","Code Description":"OK","User ID result entry":"USERNAME3","QT Result":"NOK"},
{"Order":"88879877","Inspection Lot":"22222222222","Material":"11111111","Material Description":"Noodles 2 Min","Date Result entry":"09/27/2020","Time result entry":"02:37:18 AM","Insp Point Identification":"20200926|013715|","Work center":"NLEPACK6","Operation Description":"DTMDL @ Every 4hr","Short Text Insp Char":"MOPDCTOR check","Target Value":"","Upper Tol Limit":"","Lower Tol Limit":"","Attribute":"","Unit of Measure":"","Char Valuation":"A","Code Catalog":"002","Code Description":"Ok","User ID result entry":"USERNAME6","QT Result":"NOK"},
{"Order":"88879877","Inspection Lot":"22222222222","Material":"11111111","Material Description":"Noodles 2 Min","Date Result entry":"09/25/2020","Time result entry":"04:43:50 AM","Insp Point Identification":"20200925|044342|","Work center":"NLEPACK5","Operation Description":"NPL5 @ Start up of Each Shift","Short Text Insp Char":"MOPDCTOR check","Target Value":"","Upper Tol Limit":"","Lower Tol Limit":"","Attribute":"","Unit of Measure":"","Char Valuation":"A","Code Catalog":"001","Code Description":"OK","User ID result entry":"USERNAME1","QT Result":"OK"},
{"Order":"88879877","Inspection Lot":"22222222222","Material":"11111111","Material Description":"Noodles 2 Min","Date Result entry":"09/25/2020","Time result entry":"09:27:48 PM","Insp Point Identification":"20200925|212736|","Work center":"NLEPACK5","Operation Description":"NPL5 @ Start up of Each Shift","Short Text Insp Char":"MOPDCTOR check","Target Value":"","Upper Tol Limit":"","Lower Tol Limit":"","Attribute":"","Unit of Measure":"","Char Valuation":"A","Code Catalog":"001","Code Description":"OK","User ID result entry":"USERNAME3","QT Result":"OK"},
{"Order":"88879877","Inspection Lot":"22222222222","Material":"11111111","Material Description":"Noodles 2 Min","Date Result entry":"09/25/2020","Time result entry":"04:43:48 AM","Insp Point Identification":"20200925|044342|","Work center":"NLEPACK5","Operation Description":"NPL5 @ Start up of Each Shift","Short Text Insp Char":"PCKSL Check","Target Value":"","Upper Tol Limit":"","Lower Tol Limit":"","Attribute":"","Unit of Measure":"","Char Valuation":"A","Code Catalog":"001","Code Description":"OK","User ID result entry":"USERNAME1","QT Result":"OK"},
{"Order":"88879877","Inspection Lot":"22222222222","Material":"11111111","Material Description":"Noodles 2 Min","Date Result entry":"09/25/2020","Time result entry":"02:43:47 PM","Insp Point Identification":"20200925|144336|","Work center":"NLEPACK5","Operation Description":"NPL5 @ Start up of Each Shift","Short Text Insp Char":"PCKSL Check","Target Value":"","Upper Tol Limit":"","Lower Tol Limit":"","Attribute":"","Unit of Measure":"","Char Valuation":"A","Code Catalog":"001","Code Description":"OK","User ID result entry":"USERNAME2","QT Result":"NOK"},
{"Order":"88879877","Inspection Lot":"22222222222","Material":"11111111","Material Description":"Noodles 2 Min","Date Result entry":"09/25/2020","Time result entry":"09:27:46 PM","Insp Point Identification":"20200925|212736|","Work center":"NLEPACK5","Operation Description":"NPL5 @ Start up of Each Shift","Short Text Insp Char":"PCKSL Check","Target Value":"","Upper Tol Limit":"","Lower Tol Limit":"","Attribute":"","Unit of Measure":"","Char Valuation":"A","Code Catalog":"001","Code Description":"OK","User ID result entry":"USERNAME3","QT Result":"OK"}
]
